pinboard_mcp_server/__init__.py
pinboard_mcp_server/client.py
pinboard_mcp_server/main.py
pinboard_mcp_server/models.py
pinboard_mcp_server-1.0.0.dist-info/METADATA
pinboard_mcp_server-1.0.0.dist-info/WHEEL
pinboard_mcp_server-1.0.0.dist-info/entry_points.txt
pinboard_mcp_server-1.0.0.dist-info/top_level.txt
pinboard_mcp_server-1.0.0.dist-info/RECORD
