Metadata-Version: 2.4
Name: pinboard-mcp-server
Version: 1.0.0
Summary: Pinboard MCP Server - Read-only access to Pinboard bookmarks for LLMs
Author: Pinboard MCP Server Team
License: MIT
Project-URL: Homepage, https://github.com/rossshannon/pinboard-bookmarks-mcp-server
Project-URL: Repository, https://github.com/rossshannon/pinboard-bookmarks-mcp-server
Project-URL: Issues, https://github.com/rossshannon/pinboard-bookmarks-mcp-server/issues
Classifier: Development Status :: 5 - Production/Stable
Classifier: Intended Audience :: Developers
Classifier: License :: OSI Approved :: MIT License
Classifier: Programming Language :: Python :: 3
Classifier: Programming Language :: Python :: 3.10
Classifier: Programming Language :: Python :: 3.11
Classifier: Programming Language :: Python :: 3.12
Classifier: Programming Language :: Python :: 3.13
Requires-Python: >=3.10
Requires-Dist: fastmcp>=2.0.0
Requires-Dist: pinboard>=2.0.0
Requires-Dist: pydantic>=2.0.0
Requires-Dist: python-dateutil>=2.8.0
Requires-Dist: cachetools>=5.3.0
Provides-Extra: dev
Requires-Dist: pytest>=7.4.0; extra == "dev"
Requires-Dist: pytest-asyncio>=0.21.0; extra == "dev"
Requires-Dist: pytest-cov>=4.1.0; extra == "dev"
Requires-Dist: pytest-mock>=3.11.0; extra == "dev"
Requires-Dist: ruff>=0.1.0; extra == "dev"
Requires-Dist: mypy>=1.6.0; extra == "dev"
Requires-Dist: types-python-dateutil; extra == "dev"
Requires-Dist: types-cachetools; extra == "dev"
Requires-Dist: responses>=0.23.0; extra == "dev"
Requires-Dist: vcrpy>=5.1.0; extra == "dev"
Provides-Extra: mcp
Requires-Dist: mcp>=1.0.0; extra == "mcp"
